xboolarray/__init__.py
xboolarray/xboolarray.py
xboolarray-0.1.0.dist-info/LICENCE
xboolarray-0.1.0.dist-info/METADATA
xboolarray-0.1.0.dist-info/WHEEL
xboolarray-0.1.0.dist-info/RECORD
