Metadata-Version: 2.3
Name: xboolarray
Version: 0.1.0
Summary: XBoolArray: A multidimensional boolean array with annotated dimensions and coordinates.
Author: Alessandro Lussana
Author-email: alessandro.lussana@proton.me
Requires-Python: >=3.10
Classifier: Programming Language :: Python :: 3
Classifier: Programming Language :: Python :: 3.10
Classifier: Programming Language :: Python :: 3.11
Classifier: Programming Language :: Python :: 3.12
Classifier: Programming Language :: Python :: 3.13
Requires-Dist: numpy (>=2.0.0,<3.0.0)
Requires-Dist: xarray (>=2024.10.0,<2026.0.0)
